LICENSE
MANIFEST.in
setup.cfg
setup.py
d3flux/__init__.py
d3flux.egg-info/PKG-INFO
d3flux.egg-info/SOURCES.txt
d3flux.egg-info/dependency_links.txt
d3flux.egg-info/requires.txt
d3flux.egg-info/top_level.txt
d3flux/core/__init__.py
d3flux/core/display_tools.py
d3flux/core/flux_layouts.py
d3flux/templates/__init__.py
d3flux/templates/d3flux.js
d3flux/templates/network_style.css
d3flux/templates/output_template.html